Workbook

Sheet Cover
A1: INDIAN ENERGY EXCHANGE (NSE: IEX)
A2: Short Thesis: Market Coupling and the End of the Liquidity Moat
A4: THE PITCH IN THREE SENTENCES
A5: CERC's market coupling mandate will centralise electricity price discovery across all power exchanges, and the direction of that policy is no longer in question, only its timing. IEX's 85-90% Day-Ahead Market share is a function of liquidity, which coupling makes irrelevant, so its premium pricing power should compress even if a residual customer relationship survives. At INR 120, the market is pricing in something close to the bull case (moat mostly intact); this model argues the base case (partial share and fee erosion) is more likely and implies roughly 45-50% downside, with a further, less likely bear case implying over 70% downside.
A13: Recommendation | B13: SHORT / SELL (illustrative, educational exercise -- not investment advice)
A15: Catalyst | B15: Supreme Court ruling on IEX's challenge to market coupling; CERC's final notification following the Grid India technical review. Both outstanding as of Sept 2026, no confirmed date.
A17: Current price (confirmed live) | B17: INR 113.90, confirmed 13-Sep-2026 (kotakneo.com live quote). No longer an approximation.
A19: Base case target | B19: INR 58 (-49% vs current price)
A21: Bear case target | B21: INR 31 (-73% vs current price)
A23: Bull case target (the risk to being short) | B23: INR 147 (+29% vs current price): if API-based customer lock-in fully offsets uniform pricing
A25: Sources | B25: Public news coverage of the CERC market coupling proceeding, IEX's own investor disclosures (Screener.in, exchange filings), and analyst commentary reported in the financial press. No non-public information of any kind was used.
A27: Disclaimer | B27: Educational exercise built for interview preparation. Not investment research, not a recommendation to buy or sell any security, and not based on any professional research mandate.

Sheet Assumptions
A1: CURRENT STATE AND SCENARIO ASSUMPTIONS
A2: Every yellow cell is an input you own and must justify before presenting this model.
A4: CURRENT STATE (approx, Sept 2026 -- verify against a live quote)
A5: Current share price (INR) | B5: 113.9 | D5: CONFIRMED 13-Sep-2026: kotakneo.com live quote, Rs 113.90 (day range Rs 113.00-115.91). This IS the live price on the memo date.
A6: Market capitalisation (INR Cr) | B6: 10517.52 | D6: CONFIRMED 13-Sep-2026: indmoney.com, Rs 10,517.52 Cr (as of 10-Sep-2026 intraday).
A7: Implied diluted shares (Cr) | B7: =B6/B5 -> 92.339947 | D7: NOTE: back-derived from two different vendor snapshots taken at slightly different times; will not perfectly match IEX's own reported diluted share count in its filings.
A8: TTM revenue (INR Cr) | B8: 624 | D8: Screener.in, TTM as of approx Sept 2026.
A9: TTM net profit (INR Cr) | B9: 487 | D9: Screener.in, TTM as of approx Sept 2026.
A10: TTM PAT margin | B10: =B9/B8 -> 0.78044872
A11: TTM EPS (INR) | B11: =B9/B7 -> 5.2739904
A12: Implied current P/E | B12: =B5/B11 -> 21.59655
A13: IEX's own FY26 traded volume (billion units, BU) | B13: 145 | D13: Derived from FY25's reported 121 BU and ~19-20% YoY volume growth seen in recent monthly prints.
A14: IEX's current share of total exchange-traded market | B14: 0.87 | D14: Widely reported 85-90% Day-Ahead Market share; midpoint used.
A15: Implied total exchange-traded market, FY26 (BU) | B15: =B13/B14 -> 166.66667
A16: IEX's current take rate (INR Cr revenue per BU traded) | B16: =B8/B13 -> 4.3034483 | D16: This is IEX's own blended fee per unit of electricity traded on its platform.
A18: FORWARD MARKET ASSUMPTION
A19: Total exchange-traded market CAGR (2-year forward) | B19: 0.16 | D19: Underlying secular growth: rising renewable capacity, gradual shift from long-term PPAs to short-term exchange trading. This is a growing-pie assumption independent of who captures share.
A20: Forward horizon (years) | B20: 2 | D20: To FY28, matching the timeframe most analyst share-loss estimates use.
A21: Implied total exchange-traded market, FY28E (BU) | B21: =B15*(1+B19)^B20 -> 224.26667
A23: SCENARIO DEFINITIONS (FY28E)
A25: Scenario | B25: BULL | C25: BASE | D25: BEAR
A26: FY28E market share | B26: 0.7 | C26: 0.57 | D26: 0.5 | F26: BULL: API-based 'tight coupling' with 70%+ of members preserves most switching friction. BASE: meaningful but partial erosion. BEAR: matches published analyst projections of ~50% by FY28.
A27: Take rate change vs today | B27: -0.08 | C27: -0.25 | D27: -0.35 | F27: How much IEX's blended fee per unit compresses as uniform pricing removes its differentiation.
A28: FY28E PAT margin | B28: 0.78 | C28: 0.72 | D28: 0.65 | F28: High fixed-cost, asset-light exchange economics mean margin holds best when share/pricing hold; competitive response (marketing, fee wars) compresses margin further in weaker scenarios.
A29: Exit P/E multiple | B29: 28 | C29: 18 | D29: 14 | F29: BULL: re-rates as a proven monopoly. BASE: 'show me' multiple, still uncertain. BEAR: structurally impaired, low-growth multiple.

Sheet Scenario Model
A1: SCENARIO MODEL -- FY28E
A2: Each column is fully independent and formula-driven off the Assumptions tab.
A4: Scenario | B4: BULL | C4: BASE | D4: BEAR
A5: FY28E total market volume (BU) | B5: =Assumptions!$B$21 -> 224.26667 | C5: =Assumptions!$B$21 -> 224.26667 | D5: =Assumptions!$B$21 -> 224.26667
A6: x IEX market share | B6: =Assumptions!B$26 -> 0.7 | C6: =Assumptions!C$26 -> 0.57 | D6: =Assumptions!D$26 -> 0.5
A7: IEX FY28E traded volume (BU) | B7: =B5*B6 -> 156.98667 | C7: =C5*C6 -> 127.832 | D7: =D5*D6 -> 112.13333
A9: Current take rate (INR Cr / BU) | B9: =Assumptions!$B$16 -> 4.3034483 | C9: =Assumptions!$B$16 -> 4.3034483 | D9: =Assumptions!$B$16 -> 4.3034483
A10: x (1 + take rate change) | B10: =1+Assumptions!B$27 -> 0.92 | C10: =1+Assumptions!C$27 -> 0.75 | D10: =1+Assumptions!D$27 -> 0.65
A11: FY28E take rate (INR Cr / BU) | B11: =B9*B10 -> 3.9591724 | C11: =C9*C10 -> 3.2275862 | D11: =D9*D10 -> 2.7972414
A13: FY28E revenue (INR Cr) | B13: =B7*B11 -> 621.53728 | C13: =C7*C11 -> 412.5888 | D13: =D7*D11 -> 313.664
A14: x PAT margin | B14: =Assumptions!B$28 -> 0.78 | C14: =Assumptions!C$28 -> 0.72 | D14: =Assumptions!D$28 -> 0.65
A15: FY28E net profit (INR Cr) | B15: =B13*B14 -> 484.79908 | C15: =C13*C14 -> 297.06394 | D15: =D13*D14 -> 203.8816
A17: Diluted shares (Cr) | B17: =Assumptions!$B$7 -> 92.339947 | C17: =Assumptions!$B$7 -> 92.339947 | D17: =Assumptions!$B$7 -> 92.339947
A18: FY28E EPS (INR) | B18: =B15/B17 -> 5.2501555 | C18: =C15/C17 -> 3.2170685 | D18: =D15/D17 -> 2.2079458
A19: x Exit P/E multiple | B19: =Assumptions!B$29 -> 28 | C19: =Assumptions!C$29 -> 18 | D19: =Assumptions!D$29 -> 14
A20: FY28E TARGET PRICE (INR) | B20: =B18*B19 -> 147.00435 | C20: =C18*C19 -> 57.907233 | D20: =D18*D19 -> 30.911241
A22: Current price (INR) | B22: =Assumptions!$B$5 -> 113.9 | C22: =Assumptions!$B$5 -> 113.9 | D22: =Assumptions!$B$5 -> 113.9
A23: IMPLIED RETURN | B23: =B20/B22-1 -> 0.29064401 | C23: =C20/C22-1 -> -0.49159585 | D23: =D20/D22-1 -> -0.7286107

Sheet Downside Bridge
A1: DOWNSIDE BRIDGE: WHERE THE RETURN COMES FROM
A2: Decomposes the BASE and BEAR case returns into the EPS-decline effect and the multiple-compression effect, holding the other constant -- same technique as the LBO returns bridge in the companion Havells repo, applied here to a short thesis.
B4: BASE | C4: BEAR
A5: Current EPS (INR) | B5: =Assumptions!$B$11 -> 5.2739904 | C5: =Assumptions!$B$11 -> 5.2739904
A6: Scenario EPS (INR) | B6: ='Scenario Model'!C18 -> 3.2170685 | C6: ='Scenario Model'!D18 -> 2.2079458
A7: Current P/E (as implied today) | B7: =Assumptions!$B$12 -> 21.59655 | C7: =Assumptions!$B$12 -> 21.59655
A8: Price if EPS falls, multiple UNCHANGED (INR) | B8: =B6*B7 -> 69.477582 | C8: =C6*C7 -> 47.684013
A9: return from EPS decline alone | B9: =B8/Assumptions!$B$5-1 -> -0.39001245 | C9: =C8/Assumptions!$B$5-1 -> -0.58135195
A10: Scenario exit multiple | B10: ='Scenario Model'!C19 -> 18 | C10: ='Scenario Model'!D19 -> 14
A11: Price if multiple ALSO compresses (INR) = full target | B11: =B6*B10 -> 57.907233 | C11: =C6*C10 -> 30.911241
A12: additional return from multiple compression | B12: =B11/B8-1 -> -0.16653356 | C12: =C11/C8-1 -> -0.35174832
A13: TOTAL IMPLIED RETURN (check vs Scenario Model tab) | B13: =B11/Assumptions!$B$5-1 -> -0.49159585 | C13: =C11/Assumptions!$B$5-1 -> -0.7286107
A16: READING THIS
A17: In both scenarios, most of the downside comes from the EPS decline itself (IEX simply earning less), not from the market additionally punishing the stock with a lower multiple. That matters for the pitch: you do not need to argue the market will panic and de-rate the stock unfairly. You only need the earnings decline to happen, and the price follows mechanically even at an unchanged multiple. The multiple compression is upside to the thesis, not the load-bearing assumption.

Sheet Sensitivity
A1: SENSITIVITY: MARKET SHARE x TAKE-RATE COMPRESSION
A2: Implied target price (INR) at a fixed 18x exit multiple (the BASE case multiple), so the grid isolates the operating assumptions from the re-rating assumption.
B5: Share \ Take-rate chg | C5: 0% | D5: -10% | E5: -20% | F5: -25% | G5: -30% | H5: -40%
B6: 85% | C6: =(((((Assumptions!$B$21*0.85)*(Assumptions!$B$16*(1+0)))*0.72)/Assumptions!$B$7)*18) -> 115.13719 | D6: =(((((Assumptions!$B$21*0.85)*(Assumptions!$B$16*(1+-0.1)))*0.72)/Assumptions!$B$7)*18) -> 103.62347 | E6: =(((((Assumptions!$B$21*0.85)*(Assumptions!$B$16*(1+-0.2)))*0.72)/Assumptions!$B$7)*18) -> 92.109751 | F6: =(((((Assumptions!$B$21*0.85)*(Assumptions!$B$16*(1+-0.25)))*0.72)/Assumptions!$B$7)*18) -> 86.352891 | G6: =(((((Assumptions!$B$21*0.85)*(Assumptions!$B$16*(1+-0.3)))*0.72)/Assumptions!$B$7)*18) -> 80.596032 | H6: =(((((Assumptions!$B$21*0.85)*(Assumptions!$B$16*(1+-0.4)))*0.72)/Assumptions!$B$7)*18) -> 69.082313
B7: 75% | C7: =(((((Assumptions!$B$21*0.75)*(Assumptions!$B$16*(1+0)))*0.72)/Assumptions!$B$7)*18) -> 101.59164 | D7: =(((((Assumptions!$B$21*0.75)*(Assumptions!$B$16*(1+-0.1)))*0.72)/Assumptions!$B$7)*18) -> 91.432473 | E7: =(((((Assumptions!$B$21*0.75)*(Assumptions!$B$16*(1+-0.2)))*0.72)/Assumptions!$B$7)*18) -> 81.27331 | F7: =(((((Assumptions!$B$21*0.75)*(Assumptions!$B$16*(1+-0.25)))*0.72)/Assumptions!$B$7)*18) -> 76.193728 | G7: =(((((Assumptions!$B$21*0.75)*(Assumptions!$B$16*(1+-0.3)))*0.72)/Assumptions!$B$7)*18) -> 71.114146 | H7: =(((((Assumptions!$B$21*0.75)*(Assumptions!$B$16*(1+-0.4)))*0.72)/Assumptions!$B$7)*18) -> 60.954982
B8: 65% | C8: =(((((Assumptions!$B$21*0.65)*(Assumptions!$B$16*(1+0)))*0.72)/Assumptions!$B$7)*18) -> 88.046085 | D8: =(((((Assumptions!$B$21*0.65)*(Assumptions!$B$16*(1+-0.1)))*0.72)/Assumptions!$B$7)*18) -> 79.241477 | E8: =(((((Assumptions!$B$21*0.65)*(Assumptions!$B$16*(1+-0.2)))*0.72)/Assumptions!$B$7)*18) -> 70.436868 | F8: =(((((Assumptions!$B$21*0.65)*(Assumptions!$B$16*(1+-0.25)))*0.72)/Assumptions!$B$7)*18) -> 66.034564 | G8: =(((((Assumptions!$B$21*0.65)*(Assumptions!$B$16*(1+-0.3)))*0.72)/Assumptions!$B$7)*18) -> 61.63226 | H8: =(((((Assumptions!$B$21*0.65)*(Assumptions!$B$16*(1+-0.4)))*0.72)/Assumptions!$B$7)*18) -> 52.827651
B9: 57% | C9: =(((((Assumptions!$B$21*0.57)*(Assumptions!$B$16*(1+0)))*0.72)/Assumptions!$B$7)*18) -> 77.209644 | D9: =(((((Assumptions!$B$21*0.57)*(Assumptions!$B$16*(1+-0.1)))*0.72)/Assumptions!$B$7)*18) -> 69.48868 | E9: =(((((Assumptions!$B$21*0.57)*(Assumptions!$B$16*(1+-0.2)))*0.72)/Assumptions!$B$7)*18) -> 61.767715 | F9: =(((((Assumptions!$B$21*0.57)*(Assumptions!$B$16*(1+-0.25)))*0.72)/Assumptions!$B$7)*18) -> 57.907233 | G9: =(((((Assumptions!$B$21*0.57)*(Assumptions!$B$16*(1+-0.3)))*0.72)/Assumptions!$B$7)*18) -> 54.046751 | H9: =(((((Assumptions!$B$21*0.57)*(Assumptions!$B$16*(1+-0.4)))*0.72)/Assumptions!$B$7)*18) -> 46.325786
B10: 50% | C10: =(((((Assumptions!$B$21*0.5)*(Assumptions!$B$16*(1+0)))*0.72)/Assumptions!$B$7)*18) -> 67.727758 | D10: =(((((Assumptions!$B$21*0.5)*(Assumptions!$B$16*(1+-0.1)))*0.72)/Assumptions!$B$7)*18) -> 60.954982 | E10: =(((((Assumptions!$B$21*0.5)*(Assumptions!$B$16*(1+-0.2)))*0.72)/Assumptions!$B$7)*18) -> 54.182206 | F10: =(((((Assumptions!$B$21*0.5)*(Assumptions!$B$16*(1+-0.25)))*0.72)/Assumptions!$B$7)*18) -> 50.795818 | G10: =(((((Assumptions!$B$21*0.5)*(Assumptions!$B$16*(1+-0.3)))*0.72)/Assumptions!$B$7)*18) -> 47.409431 | H10: =(((((Assumptions!$B$21*0.5)*(Assumptions!$B$16*(1+-0.4)))*0.72)/Assumptions!$B$7)*18) -> 40.636655
B11: 40% | C11: =(((((Assumptions!$B$21*0.4)*(Assumptions!$B$16*(1+0)))*0.72)/Assumptions!$B$7)*18) -> 54.182206 | D11: =(((((Assumptions!$B$21*0.4)*(Assumptions!$B$16*(1+-0.1)))*0.72)/Assumptions!$B$7)*18) -> 48.763986 | E11: =(((((Assumptions!$B$21*0.4)*(Assumptions!$B$16*(1+-0.2)))*0.72)/Assumptions!$B$7)*18) -> 43.345765 | F11: =(((((Assumptions!$B$21*0.4)*(Assumptions!$B$16*(1+-0.25)))*0.72)/Assumptions!$B$7)*18) -> 40.636655 | G11: =(((((Assumptions!$B$21*0.4)*(Assumptions!$B$16*(1+-0.3)))*0.72)/Assumptions!$B$7)*18) -> 37.927544 | H11: =(((((Assumptions!$B$21*0.4)*(Assumptions!$B$16*(1+-0.4)))*0.72)/Assumptions!$B$7)*18) -> 32.509324
A14: Current price for reference (INR) | B14: =Assumptions!$B$5 -> 113.9
A15: NOTE
A16: PAT margin held fixed at 72% (the BASE case) throughout this grid so it isolates only share and take-rate, the two variables the market coupling debate is actually about. Every cell below the current price row is a scenario in which the short thesis is right.

Sheet Catalyst Timeline
A1: CATALYST TIMELINE
A2: Dated or approximately-dated events that could force a re-rating in either direction. None of these dates are confirmed by IEX or CERC as of the build date -- verify each before citing it.
A4: Date / Status | B4: Event | C4: Why it matters
A5: Jul 2025 | B5: CERC's original market coupling order | C5: The regulatory direction was set here; the stock fell ~30% in a single session.
A6: Feb 2026 | B6: APTEL (appellate tribunal) dismisses IEX's initial legal challenge | C6: First sign the legal path favours implementation, not IEX.
A7: Apr 2026 | B7: CERC issues draft Second Amendment Regulations; Grid India raises its own technical objections | C7: A regulator's own implementation partner questioning execution readiness is a stronger delay signal than IEX's objections alone.
A8: Ongoing, 2026 | B8: Supreme Court agrees to examine IEX's plea | C8: The highest possible legal escalation; a ruling either way is the clearest re-rating catalyst on the table.
A9: Quarterly | B9: IEX volume and revenue prints | C9: Watch for early signs of share loss or fee pressure showing up in the numbers ahead of coupling's actual launch.
A10: Unconfirmed | B10: Final CERC notification and Power Market Coupling Procedure (PMCP) publication by Grid India | C10: The actual implementation date; every delay here is a reason the BULL case can persist longer than the BEAR case assumes.

Sheet Comps
A1: COMPARABLE COMPANY CHECK: WHAT MOAT-INTACT INDIAN MARKET INFRASTRUCTURE TRADES AT
A2: Sourced 13-Sep-2026. These are the businesses IEX most resembles structurally (near-monopoly, asset-light, high-margin market infrastructure) BEFORE the market coupling threat. Used to sanity-check, not set, the exit multiples on the Scenario Model tab.
A4: Company | B4: Business | C4: P/E | D4: Source, 13-Sep-2026
A5: MCX (Multi Commodity Exchange) | B5: India's dominant commodity derivatives exchange, near-monopoly | C5: 56.6 | D5: valueresearchonline.com, 29-May-2026 (P/E 56.60x, peer median 60.51x)
A6: CDSL (Central Depository Services) | B6: Depository duopoly, 120M+ demat accounts, recurring AMC/fee income | C6: 60.5 | D6: Derived: Screener.in market cap Rs 28,424 Cr / TTM profit Rs 470 Cr
A7: CAMS (Computer Age Management Services) | B7: Mutual fund registrar/transfer agent, dominant market share | C7: 36.1 | D7: dhan.co live quote, 11-Sep-2026
A9: Peer median P/E (moat-intact market infrastructure) | C9: =MEDIAN(C5:C7) -> 56.6
A11: IEX current TTM P/E (at today's price, reflecting the regulatory discount) | C11: =Assumptions!B5/Assumptions!B11 -> 21.59655
A13: Implied discount to peers already priced in | C13: =1-C11/C9 -> 0.61843551
A16: READING THIS AGAINST THE SCENARIO MODEL'S EXIT MULTIPLES
A17: IEX already trades at a large discount to peers with an intact moat, which is exactly what the market coupling threat would predict. This is a genuine cross-check on the three exit multiples used on the Scenario Model tab, not just an assertion: the BULL case (28x) sits well BELOW the peer median above, meaning that even in the scenario where IEX's moat mostly survives, the model does not assume IEX re-rates all the way back to where MCX or CDSL trade, a conservative choice, if anything. The BASE (18x) and BEAR (14x) cases sit further below still, consistent with a business that has lost the structural characteristic (near-monopoly liquidity) that lets these peers command 36-60x. If a bull case wanted to argue IEX fully re-rates to the peer median once coupling is defeated or delayed indefinitely, that would imply a target price meaningfully ABOVE this model's own bull case: worth stating explicitly as the true upside risk to being short, rather than treating 28x as the ceiling.
